{
    "moviename ": "Apur Sansar",
    "movie time": "1 hour 45 minutes",
    "Poster URL": "www.imdb.comhttps://m.media-amazon.com/images/M/MV5BN2ZhM2NkZDUtMTI3OC00NWE5LWEwYzMtZTlhMjhkZGFlMjQyXkEyXkFqcGdeQXVyNTgyNTA4MjM@._V1_QL75_UX190_CR0,2,190,281_.jpg",
    "movie genere": [
        "Drama"
    ],
    "Bio": "This final installment in Satyajit Ray's Apu Trilogy follows Apu's life as an orphaned adult aspiring to be a writer.",
    "movie director": [
        "Satyajit Ray"
    ],
    "countries": [
        "India"
    ],
    "languages": [
        "Bengali"
    ]
}