{
    "moviename ": "Anniyan",
    "movie time": "3 hours 3 minutes",
    "Poster URL": "www.imdb.comhttps://m.media-amazon.com/images/M/MV5BNmU1MWNjNmItMzRkMy00MWQ0LThhZjYtODE5Y2EyODk2YjQ2XkEyXkFqcGdeQXVyNTgyNTA4MjM@._V1_QL75_UX190_CR0,2,190,281_.jpg",
    "movie genere": [
        "Action",
        "Drama",
        "Thriller"
    ],
    "Bio": "Ramanujam, who suffers from multiple personality disorder, works as a lawyer by day and a vigilante at night. He uses tips from the 'Garuda Purana' as his tools to expose various antisocial elements.",
    "movie director": [
        "S. Shankar"
    ],
    "countries": [
        "India"
    ],
    "languages": [
        "Tamil"
    ]
}